mcfinance/__init__.py
mcfinance/extractors.py
mcfinance/helper.py
mcfinance/retrieval.py
mcfinance/writer.py
mcfinance/data/dictbse.json
mcfinance/data/dictnse.json
mcfinance-0.1.8.dist-info/LICENSE
mcfinance-0.1.8.dist-info/METADATA
mcfinance-0.1.8.dist-info/WHEEL
mcfinance-0.1.8.dist-info/top_level.txt
mcfinance-0.1.8.dist-info/RECORD
