Metadata-Version: 2.1
Name: mcfinance
Version: 0.1.8
Summary: Money control financial data extractor-Requires python 3.7+
Author: 05kashyap-ragha1992
Author-email: <aryankashyapnaveen@gmail.com>
Keywords: python,financial,extractor,data
Classifier: Development Status :: 3 - Alpha
Classifier: Intended Audience :: Developers
Classifier: Programming Language :: Python :: 3.11
Classifier: Operating System :: Microsoft :: Windows
License-File: LICENSE
Requires-Dist: pandas
Requires-Dist: bs4
Requires-Dist: html5lib
Requires-Dist: lxml
Requires-Dist: matplotlib
Requires-Dist: requests
Requires-Dist: openpyxl
Requires-Dist: PyQt5
